gabbi/__init__.py
gabbi/case.py
gabbi/driver.py
gabbi/exception.py
gabbi/fixture.py
gabbi/httpclient.py
gabbi/pytester.py
gabbi/reporter.py
gabbi/runner.py
gabbi/suite.py
gabbi/suitemaker.py
gabbi/utils.py
gabbi/handlers/__init__.py
gabbi/handlers/base.py
gabbi/handlers/core.py
gabbi/handlers/jsonhandler.py
gabbi/handlers/yaml_disk_loading_jsonhandler.py
gabbi/tests/__init__.py
gabbi/tests/custom_response_handler.py
gabbi/tests/external_server.py
gabbi/tests/simple_wsgi.py
gabbi/tests/test_data_to_string.py
gabbi/tests/test_driver.py
gabbi/tests/test_fixtures.py
gabbi/tests/test_handlers.py
gabbi/tests/test_history.py
gabbi/tests/test_inner_fixture.py
gabbi/tests/test_intercept.py
gabbi/tests/test_jsonpath.py
gabbi/tests/test_live.py
gabbi/tests/test_load_data_file.py
gabbi/tests/test_parse_url.py
gabbi/tests/test_replacers.py
gabbi/tests/test_runner.py
gabbi/tests/test_suite.py
gabbi/tests/test_suitemaker.py
gabbi/tests/test_syntax_warning.py
gabbi/tests/test_unsafe_yaml.py
gabbi/tests/test_use_prior_test.py
gabbi/tests/test_utils.py
gabbi/tests/test_yaml_disk_loading_jsonhandler.py
gabbi/tests/util.py
gabbi-4.2.0.dist-info/licenses/LICENSE
gabbi-4.2.0.dist-info/METADATA
gabbi-4.2.0.dist-info/WHEEL
gabbi-4.2.0.dist-info/top_level.txt
gabbi-4.2.0.dist-info/RECORD
