Metadata-Version: 2.4
Name: gabbi
Version: 4.2.0
Summary: Declarative HTTP testing library
Home-page: https://github.com/cdent/gabbi
Author: Chris Dent
Author-email: cdent@anticdent.org
License: Apache-2
Classifier: Intended Audience :: Developers
Classifier: Intended Audience :: Information Technology
Classifier: Environment :: Web Environment
Classifier: License :: OSI Approved :: Apache Software License
Classifier: Operating System :: POSIX
Classifier: Programming Language :: Python
Classifier: Programming Language :: Python :: 3
Classifier: Programming Language :: Python :: 3.9
Classifier: Programming Language :: Python :: 3.10
Classifier: Programming Language :: Python :: 3.11
Classifier: Programming Language :: Python :: 3.12
Classifier: Programming Language :: Python :: 3.13
Classifier: Programming Language :: Python :: 3.14
Classifier: Programming Language :: Python :: 3 :: Only
Classifier: Topic :: Internet :: WWW/HTTP :: WSGI
Classifier: Topic :: Software Development :: Testing
License-File: LICENSE
Requires-Dist: pytest
Requires-Dist: PyYAML
Requires-Dist: httpx[http2]
Requires-Dist: certifi
Requires-Dist: jsonpath-ng
Requires-Dist: colorama
Dynamic: license-file
Dynamic: requires-dist
